{
  "version": "1.0",
  "instruments": [
    "EURUSD",
    "GBPUSD",
    "AUDUSD",
    "USDCAD",
    "USDCHF",
    "USDJPY",
    "GOLD",
    "OIL_CRUDE"
  ],
  "structure_watch": {
    "EURUSD": {
      "timeframes": [
        "HOUR",
        "MINUTE_15",
        "HOUR_4"
      ]
    },
    "GBPUSD": {
      "timeframes": [
        "HOUR",
        "MINUTE_15",
        "HOUR_4"
      ]
    },
    "AUDUSD": {
      "timeframes": [
        "HOUR",
        "MINUTE_15",
        "DAY"
      ]
    },
    "USDCAD": {
      "timeframes": [
        "HOUR",
        "MINUTE_15"
      ]
    },
    "USDCHF": {
      "timeframes": [
        "HOUR",
        "MINUTE_15"
      ]
    },
    "USDJPY": {
      "timeframes": [
        "HOUR",
        "MINUTE_15"
      ]
    },
    "GOLD": {
      "timeframes": [
        "HOUR",
        "MINUTE_15"
      ]
    },
    "OIL_CRUDE": {
      "timeframes": [
        "HOUR",
        "MINUTE_15"
      ]
    }
  },
  "level_alerts": [
    {
      "id": "eurusd_upsweep_117159_sell_watch",
      "alert_id": "eurusd_upsweep_117159_sell_watch",
      "instrument": "EURUSD",
      "level": 1.17159,
      "emit_on": "cross_up",
      "cooldown_sec": 1800,
      "direction": "sell",
      "active": true,
      "validated": true,
      "note": "ENTRY: M15 retest of 1.17159 with bearish rejection wick >=1p. VALIDATED \u2014 naked LIMIT SELL when comp >=+40 bullish extension (no confirmation required).\n\nCONTEXT: VALIDATED \u2014 10+ fires, 4h hit_rate=89% per Rule 3. EURUSD at 1.178015 (64.2p above level). comp=+49 >=+40 CT-fade threshold MET. Cannot place LIMIT now (price above level, >30p proximity). Watch for pullback to 1.17159 zone; arm on approach within 30p. 4h time-stop if entered.\n\nSL: 1.17189  TP: 1.17028  R:R target: 4.4\n\nupdated 2026-05-08T18:10Z \u2014 comp=+49 threshold met; price 64.2p above; WATCH for return.",
      "entry_criterion": "M15 retest of 1.17159 with bearish rejection wick >=1p. VALIDATED \u2014 naked LIMIT SELL when comp >=+40 bullish extension (no confirmation required).",
      "regime_context": "EURUSD 1.178015, comp=+49 moderate bull. H4 CHoC bull 2026-04-27. 4h time-stop if entered.",
      "sl": 1.17189,
      "tp": 1.17028,
      "rr_target": "4.4",
      "current_price_ref": 1.178015,
      "last_updated": "2026-05-08T18:10Z"
    },
    {
      "id": "usdjpy_day_fvg_sell_15733",
      "alert_id": "usdjpy_day_fvg_sell_15733",
      "instrument": "USDJPY",
      "level": 157.33,
      "emit_on": "cross_up",
      "cooldown_sec": 1800,
      "direction": "sell",
      "active": true,
      "validated": false,
      "note": "ENTRY: price retests Day FVG bottom 157.33 (Day bear FVG: 157.33-159.52, unmitigated); M15 bar closes AT or BELOW 157.33 with bearish rejection wick >=5p from the high. Arm SELL LIMIT only when comp <= -40 (moderate bear).\n\nCONTEXT: USDJPY at 156.621, comp=-29 weak bear. Price 70.9p BELOW sell level. Hormuz military escalation intensifying JPY safe-haven bid (US attacks Iranian vessel 2026-05-08T13:43Z). USDJPY likely to fall further. Level 157.33 remains valid FVG demand-turned-supply. 3xH4ATR=125.8p; dist=70.9p \u2014 not auto-removed. Arm at comp <=-40.\n\nSL: 159.60  TP: 153.80  R:R target: 1.54\n\nmodified 2026-05-08T18:10Z \u2014 price update 156.621; Hormuz JPY bid reinforces bear thesis.",
      "entry_criterion": "M15 retest of Day FVG bottom 157.33 with bearish wick >=5p. Arm SELL LIMIT at comp <=-40 moderate bear.",
      "regime_context": "USDJPY 156.621, comp=-29 weak bear. Price below sell level by 70.9p. Hormuz safe-haven JPY bid active.",
      "sl": 159.6,
      "tp": 153.8,
      "rr_target": "1.54",
      "current_price_ref": 156.621,
      "last_updated": "2026-05-08T18:10Z"
    },
    {
      "id": "usdcad_m15sweep_136540_sell_watch",
      "alert_id": "usdcad_m15sweep_136540_sell_watch",
      "instrument": "USDCAD",
      "level": 1.36606,
      "emit_on": "cross_up",
      "cooldown_sec": 1800,
      "direction": "sell",
      "active": true,
      "validated": false,
      "note": "ENTRY: M15 close BELOW 1.36579 retest of sweep zone (up-sweep 2026-05-08T12:15Z, wick 1.8p, close_inside 1.36579); SL above 1.36624; TP 1.36218. ARM only when comp <= -40.\n\nCONTEXT: USDCAD at 1.36835, comp=+5.5 none. M15 BOS bull vs H4 BOS bear conflict. Price 22.9p ABOVE sweep level (1.36835-1.36606). Fresh M15 up-sweep 12:26Z at 1.36606. USD weakness from Hormuz escalation could push USDCAD lower. Need comp <=-40 for SELL LIMIT arm. 3xH4ATR=64.2p; dist=22.9p \u2014 not auto-removed.\n\nSL: 1.36624  TP: 1.36218  R:R target: 8.0\n\nupdated 2026-05-08T18:10Z \u2014 price update 1.36835; comp still none, WATCH only.",
      "entry_criterion": "M15 close BELOW 1.36579 retest of swept extreme. ARM when comp <=-40.",
      "regime_context": "USDCAD 1.36835, comp=+5.5 none. M15 BOS bull vs H4 BOS bear. Sweep at 1.36606 fresh.",
      "sl": 1.36624,
      "tp": 1.36218,
      "rr_target": "8.0",
      "current_price_ref": 1.36835,
      "last_updated": "2026-05-08T18:10Z"
    },
    {
      "id": "usdchf_fvg_sell_78304",
      "alert_id": "usdchf_fvg_sell_78304",
      "instrument": "USDCHF",
      "level": 0.77933,
      "emit_on": "cross_up",
      "cooldown_sec": 1800,
      "direction": "sell",
      "active": true,
      "validated": false,
      "note": "ENTRY: price retests 0.77933 (H4 bear FVG bottom; FVG: 0.77933-0.77997, unmitigated); M15 bar closes AT or BELOW 0.77933 with bearish rejection wick >=2p. Arm SELL LIMIT when comp <=-40 moderate+ bear. Skip if 2+ USD-weakness positions open (correlation cap).\n\nCONTEXT: USDCHF at 0.77659, comp=-43 moderate bear. Level 0.77933 is 27.4p ABOVE current price \u2014 WITHIN 30p proximity threshold. Threshold qualifies for LIMIT arm BUT AUDUSD BUY + GBPUSD BUY = 2 USD-weakness positions = correlation cap FULL. Next available entry slot is after one USD-weakness position closes. SL above FVG top 0.77997 + buffer = 0.78047. R:R=3.8. Hormuz Hormuz CHF safe-haven bid reinforces bear bias.\n\nSL: 0.78047  TP: 0.775  R:R target: 3.8\n\nupdated 2026-05-08T18:10Z \u2014 price 0.77659 (dist=27.4p, within 30p prox); comp=-43 qualifies; blocked by 2-correlated cap.",
      "entry_criterion": "M15 retest of 0.77933 H4 bear FVG bottom with bearish rejection wick >=2p. Arm SELL LIMIT at comp <=-40. Skip if 2 USD-weakness positions open.",
      "regime_context": "USDCHF 0.77659, comp=-43 moderate bear. H4 FVG 0.77933-0.77997 unmitigated, 27.4p away. Correlation cap blocks entry.",
      "sl": 0.78047,
      "tp": 0.775,
      "rr_target": 3.8,
      "current_price_ref": 0.77659,
      "last_updated": "2026-05-08T18:10Z"
    },
    {
      "id": "oil_sweep_9323_buy_retest",
      "alert_id": "oil_sweep_9323_buy_retest",
      "instrument": "OIL_CRUDE",
      "level": 93.23,
      "emit_on": "cross_up",
      "cooldown_sec": 1800,
      "direction": "buy",
      "active": true,
      "validated": true,
      "note": "ENTRY: price retests 93.23 (swept extreme, validated 6-fire BUY pattern); M15 closes AT or ABOVE 93.23 with bullish rejection wick >=0.2 from low. Arm BUY LIMIT when comp >=+40. VALIDATED (CF: 6 fires, 83%/100% 1h/4h). 4h time-stop if entered.\n\nCONTEXT: US attacks Iranian vessel near Strait of Hormuz (2026-05-08T13:43Z); Iran seizes oil tanker (18:03Z). OIL supply-risk premium at maximum. OIL at 92.772, only 0.46 pts below level 93.23. comp=-12.5 (none) \u2014 TA bearish short-term; WATCH until comp improves to >=+40 before arming. VALIDATED pattern: once comp threshold met, arm naked LIMIT per Rule 3.\n\nSL: 92.50  TP: 95.50  R:R target: 3.1\n\nadded 2026-05-08T18:10Z \u2014 Hormuz military escalation triggers re-add; 6-fire validated CF pattern; comp=none (WATCH, arm at comp >=+40).",
      "entry_criterion": "M15 retest of 93.23 with bullish wick >=0.2. Arm BUY LIMIT at comp >=+40. VALIDATED \u2014 naked LIMIT when threshold met.",
      "regime_context": "OIL 92.772, comp=-12.5 none. Hormuz military escalation bullish for OIL. WATCH until comp >=+40.",
      "sl": 92.5,
      "tp": 95.5,
      "rr_target": 3.1,
      "current_price_ref": 92.772,
      "last_updated": "2026-05-08T18:10Z"
    }
  ]
}